README.rst
setup.py
tarantool_queue/__init__.py
tarantool_queue/tarantool_queue.py
tarantool_queue/tarantool_tqueue.py
tarantool_queue.egg-info/PKG-INFO
tarantool_queue.egg-info/SOURCES.txt
tarantool_queue.egg-info/dependency_links.txt
tarantool_queue.egg-info/requires.txt
tarantool_queue.egg-info/top_level.txt