Metadata-Version: 1.1
Name: tarantool-queue
Version: 0.1.4
Summary: Python bindings for Tarantool queue script (http://github.com/tarantool/queue)
Home-page: http://github.com/tarantool/tarantool-queue-python
Author: Eugine Blikh
Author-email: bigbes@gmail.com
License: MIT
Platform: all
Classifier: Development Status :: 4 - Beta
Classifier: Operating System :: OS Independent
Classifier: Intended Audience :: Developers
Classifier: License :: OSI Approved :: MIT License
Classifier: Programming Language :: Python :: 2.6
Classifier: Programming Language :: Python :: 2.7
Classifier: Topic :: Database :: Front-Ends
Classifier: Environment :: Console
